{"type":"Scene","props":{"width":265,"rotation":90,"name":"dialogmessage","height":480},"compId":2,"child":[{"type":"Sprite","props":{"y":-377,"x":-86,"texture":"comp/dialog.png"},"compId":5},{"type":"Sprite","props":{"y":-272,"x":435,"width":64,"var":"dialog_close","texture":"comp/close.png","name":"dialog_close","height":73},"compId":6},{"type":"Sprite","props":{"y":-86,"x":87,"width":159,"var":"dialog_yes","texture":"comp/yes.png","name":"dialog_yes","height":84},"compId":7},{"type":"Sprite","props":{"y":-86,"x":246,"width":159,"var":"dialog_no","texture":"comp/no.png","name":"dialog_no","height":84},"compId":8},{"type":"TextArea","props":{"y":-214,"x":12,"width":468,"var":"dialog_text","name":"dialog_text","height":141},"compId":9}],"loadList":["comp/dialog.png","comp/close.png","comp/yes.png","comp/no.png"],"loadList3D":[]}